tocount/__init__.py
tocount/functions.py
tocount/params.py
tocount-0.4.dist-info/licenses/AUTHORS.md
tocount-0.4.dist-info/licenses/LICENSE
tocount-0.4.dist-info/METADATA
tocount-0.4.dist-info/WHEEL
tocount-0.4.dist-info/top_level.txt
tocount-0.4.dist-info/RECORD
